[
  {
    "node_code_old": "% DESC. ANKA",
    "node_kind": "des_mat",
    "descripcion_corta": "DESC. ANKA 10%",
    "descripcion_larga": "",
    "unidad": "%",
    "selected_product_code": "DESCUENTO",
    "confidence": 1.0,
    "reason": "rule:discount_unit"
  },
  {
    "node_code_old": "% DESC. FACHADA SEGO",
    "node_kind": "partida",
    "descripcion_corta": "DESC. FACHADA SEGOVIA -5",
    "descripcion_larga": "",
    "unidad": "%",
    "selected_product_code": "DESCUENTO",
    "confidence": 1.0,
    "reason": "rule:discount_unit"
  },
  {
    "node_code_old": "07.001 DESC",
    "node_kind": "des_mat",
    "descripcion_corta": "BAJANTE PVC PLUVIALES 90 mm",
    "descripcion_larga": "",
    "unidad": "M",
    "selected_product_code": "MA1406",
    "confidence": 0.0,
    "reason": "fallback:jaccard"
  },
  {
    "node_code_old": "01.000 DESC",
    "node_kind": "des_mat",
    "descripcion_corta": "INVESTIGACION REDES DE INSTALACIONES",
    "descripcion_larga": "",
    "unidad": "UD",
    "selected_product_code": "CIMO0501",
    "confidence": 0.0,
    "reason": "fallback:jaccard"
  },
  {
    "node_code_old": "01.001 DESC",
    "node_kind": "des_mat",
    "descripcion_corta": "PICADO Y RETIRADA DE CORNISA DE HORMG. PREFAB",
    "descripcion_larga": "",
    "unidad": "M",
    "selected_product_code": "MA5301",
    "confidence": 0.0,
    "reason": "fallback:jaccard"
  },
  {
    "node_code_old": "01.002 DESC",
    "node_kind": "des_mat",
    "descripcion_corta": "DESMONT. TRAZADO INST EXIST EN DESUSO/ MODIF TRAZADO EN USO",
    "descripcion_larga": "",
    "unidad": "m2",
    "selected_product_code": "MA3101",
    "confidence": 0.0,
    "reason": "fallback:jaccard"
  },
  {
    "node_code_old": "01.003 DESC",
    "node_kind": "des_mat",
    "descripcion_corta": "DESMONTAJE BANDEJAS DE CHAPA EN CORONACION FACHADA",
    "descripcion_larga": "",
    "unidad": "M2",
    "selected_product_code": "SB3105",
    "confidence": 0.0,
    "reason": "fallback:jaccard"
  },
  {
    "node_code_old": "01.004 DESC",
    "node_kind": "des_mat",
    "descripcion_corta": "CORTE Y PERFILADO IMPOSTA/ VIERTEAGUAS PREFABRICADO",
    "descripcion_larga": "",
    "unidad": "M",
    "selected_product_code": "SB1007",
    "confidence": 0.0,
    "reason": "fallback:jaccard"
  },
  {
    "node_code_old": "01.005 DESC",
    "node_kind": "des_mat",
    "descripcion_corta": "DESMONTAJE Y RETIRADA DE BAJANTES DE PLUVIALES",
    "descripcion_larga": "",
    "unidad": "ML",
    "selected_product_code": "MA4802",
    "confidence": 0.0,
    "reason": "fallback:jaccard"
  },
  {
    "node_code_old": "01.005B DESC",
    "node_kind": "des_mat",
    "descripcion_corta": "DESMONTAJE, RETIRADA Y RETRAZADO CONDUCCIONES ESQUINA NORESTE",
    "descripcion_larga": "",
    "unidad": "UD",
    "selected_product_code": "MA3801",
    "confidence": 0.0,
    "reason": "fallback:jaccard"
  },
  {
    "node_code_old": "01.006 DESC",
    "node_kind": "des_mat",
    "descripcion_corta": "DESMONTAJE Y REPOSICIONAMIENTO DE UNID EXTERIORES CLIMAT FACHADA",
    "descripcion_larga": "",
    "unidad": "UD",
    "selected_product_code": "MA5301",
    "confidence": 0.0,
    "reason": "fallback:jaccard"
  },
  {
    "node_code_old": "01.007 DESC",
    "node_kind": "des_mat",
    "descripcion_corta": "DESMONTAJE DE REJAS METALICAS DE VENTANAS",
    "descripcion_larga": "",
    "unidad": "UD",
    "selected_product_code": "SB0407",
    "confidence": 0.0,
    "reason": "fallback:jaccard"
  },
  {
    "node_code_old": "01.008 DESC",
    "node_kind": "des_mat",
    "descripcion_corta": "DESMONTAJE DE LUMINARIAS DE FACHADA",
    "descripcion_larga": "",
    "unidad": "UD",
    "selected_product_code": "MA4204",
    "confidence": 0.0,
    "reason": "fallback:jaccard"
  },
  {
    "node_code_old": "01.009 DESC",
    "node_kind": "des_mat",
    "descripcion_corta": "DESMONTAJE CORTAVIENTOS DE ACCESO A RESIDENCIA",
    "descripcion_larga": "",
    "unidad": "UD",
    "selected_product_code": "QC0401",
    "confidence": 0.0,
    "reason": "fallback:jaccard"
  },
  {
    "node_code_old": "O DESCONEXION ELECTR",
    "node_kind": "des_mat",
    "descripcion_corta": "DESCONEXION ELECTRICA",
    "descripcion_larga": "",
    "unidad": "UD",
    "selected_product_code": "QA0101",
    "confidence": 0.0,
    "reason": "fallback:jaccard"
  },
  {
    "node_code_old": "01.010 DESC",
    "node_kind": "des_mat",
    "descripcion_corta": "PICADO Y RETIRADA DE RECERCADO HUECO ACCESO PPAL",
    "descripcion_larga": "",
    "unidad": "UD",
    "selected_product_code": "MA5301",
    "confidence": 0.0,
    "reason": "fallback:jaccard"
  },
  {
    "node_code_old": "01.011 DESC",
    "node_kind": "des_mat",
    "descripcion_corta": "DESMONTAJE DE CHIMENEA FACHADA OESTE TRASERA",
    "descripcion_larga": "",
    "unidad": "ml",
    "selected_product_code": "MA4204",
    "confidence": 0.0,
    "reason": "fallback:jaccard"
  },
  {
    "node_code_old": "01.011B DESC",
    "node_kind": "des_mat",
    "descripcion_corta": "SUM Y MONTAJE DE CHIMENEA INTERIOR ACERO INOX c/ AISLAM DINAK",
    "descripcion_larga": "",
    "unidad": "UD",
    "selected_product_code": "MA1401",
    "confidence": 0.0,
    "reason": "fallback:jaccard"
  },
  {
    "node_code_old": "chimei30d150",
    "node_kind": "des_mat",
    "descripcion_corta": "chimei30d150",
    "descripcion_larga": "",
    "unidad": "UD",
    "selected_product_code": "MA0101",
    "confidence": 0.0,
    "reason": "fallback:jaccard"
  },
  {
    "node_code_old": "01.012 DESC",
    "node_kind": "des_mat",
    "descripcion_corta": "RECOLOCACION ARMARIOS DE INSTALACIONES EN NUEVA FACHADA",
    "descripcion_larga": "",
    "unidad": "UD",
    "selected_product_code": "SB1701",
    "confidence": 0.0,
    "reason": "fallback:jaccard"
  },
  {
    "node_code_old": "01.013 DESC",
    "node_kind": "des_mat",
    "descripcion_corta": "DESMONTAJE Y REPOSICIONADO ESCALERA METALICA DE EVACUACION",
    "descripcion_larga": "",
    "unidad": "UD",
    "selected_product_code": "SB0404",
    "confidence": 0.0,
    "reason": "fallback:jaccard"
  },
  {
    "node_code_old": "01.014 DESC",
    "node_kind": "des_mat",
    "descripcion_corta": "DESMONTAJE Y REUBICACION DE PLACAS",
    "descripcion_larga": "",
    "unidad": "UD",
    "selected_product_code": "MA4603",
    "confidence": 0.0,
    "reason": "fallback:jaccard"
  },
  {
    "node_code_old": "01.015 DESC",
    "node_kind": "des_mat",
    "descripcion_corta": "DESMONTAJE Y REUBICACION UNIDADES EXTERIORES CLIMAT. PATIO",
    "descripcion_larga": "",
    "unidad": "UD",
    "selected_product_code": "MA1701",
    "confidence": 0.0,
    "reason": "fallback:jaccard"
  },
  {
    "node_code_old": "recogidagas",
    "node_kind": "des_mat",
    "descripcion_corta": "recogidagas",
    "descripcion_larga": "",
    "unidad": "UD",
    "selected_product_code": "MA0101",
    "confidence": 0.0,
    "reason": "fallback:jaccard"
  },
  {
    "node_code_old": "tfrigorifica",
    "node_kind": "des_mat",
    "descripcion_corta": "tfrigorifica",
    "descripcion_larga": "",
    "unidad": "UD",
    "selected_product_code": "MA0101",
    "confidence": 0.0,
    "reason": "fallback:jaccard"
  },
  {
    "node_code_old": "01.016.1",
    "node_kind": "des_mat",
    "descripcion_corta": "DEMOLICION COMPLETA ALMACEN EXTERIOR DE RESIDUOS",
    "descripcion_larga": "UD. Demolicion completa de almacen exterior de residuos, formado por tapias de fabrica de ladrillo o bloque enfoscado, pavimento de baldosa ceramica, solera, cimentaciones, etc, dejando el ambito completamente exento de elementos de fabrica y/ o hormigon para poder acometer la nueva intervencion.",
    "unidad": "UD",
    "selected_product_code": "MA3303",
    "confidence": 0.0,
    "reason": "fallback:jaccard"
  },
  {
    "node_code_old": "01.016B DESC",
    "node_kind": "des_mat",
    "descripcion_corta": "DESMONTAJE DE CIERRE DE CHAPA METALICA",
    "descripcion_larga": "",
    "unidad": "M2",
    "selected_product_code": "SB0404",
    "confidence": 0.0,
    "reason": "fallback:jaccard"
  },
  {
    "node_code_old": "01.017 DESC",
    "node_kind": "des_mat",
    "descripcion_corta": "DEMOLICION DE CIERRE MURO HORMION Y CHAPADO",
    "descripcion_larga": "",
    "unidad": "m3",
    "selected_product_code": "MA5301",
    "confidence": 0.0,
    "reason": "fallback:jaccard"
  },
  {
    "node_code_old": "O DESMONTAJE PUERTAS",
    "node_kind": "des_mat",
    "descripcion_corta": "O DESMONTAJE PUERTAS",
    "descripcion_larga": "",
    "unidad": "UD",
    "selected_product_code": "MA1409",
    "confidence": 0.0,
    "reason": "fallback:jaccard"
  },
  {
    "node_code_old": "O DESMONTAJE ESCALER",
    "node_kind": "des_mat",
    "descripcion_corta": "O DESMONTAJE ESCALERA",
    "descripcion_larga": "",
    "unidad": "UD",
    "selected_product_code": "SB0302",
    "confidence": 0.0,
    "reason": "fallback:jaccard"
  },
  {
    "node_code_old": "O DEMOLICION VIDRIO",
    "node_kind": "des_mat",
    "descripcion_corta": "O DEMOLICION VIDRIO",
    "descripcion_larga": "",
    "unidad": "m2",
    "selected_product_code": "SB0302",
    "confidence": 0.0,
    "reason": "fallback:jaccard"
  },
  {
    "node_code_old": "01.018 DESC",
    "node_kind": "des_mat",
    "descripcion_corta": "DESMANTELAMIENTO DE MURETES Y BANCOS DE LA PLAZA",
    "descripcion_larga": "",
    "unidad": "UD",
    "selected_product_code": "QC0901",
    "confidence": 0.0,
    "reason": "fallback:jaccard"
  },
  {
    "node_code_old": "01.018B.1",
    "node_kind": "des_mat",
    "descripcion_corta": "DEMOLICION PAVIMENTO EXTERIOR S/CAPA MORTERO",
    "descripcion_larga": "M2. Demolicion de pavimento exterior formado por baldosas de piedra, adoquin prefabricado, asfalto, baldosa hidraulica, etc, sobre capa de mortero de cemento, incluida esta, con medios manuales y equipos mecanicos, en la superficie especificada en planos.",
    "unidad": "M2",
    "selected_product_code": "SM3905",
    "confidence": 0.0,
    "reason": "fallback:jaccard"
  },
  {
    "node_code_old": "01.018C.1",
    "node_kind": "des_mat",
    "descripcion_corta": "DEMOLICION SOLERA EXTERIOR H. ARMADO",
    "descripcion_larga": "M2. Demolicion de solera exterior de hormigon ligeramente armado, de 10 cm de espesor medio, con medios manuales y equipos mecanicos, en la superficie especificada en planos.",
    "unidad": "M2",
    "selected_product_code": "SM3802",
    "confidence": 0.0,
    "reason": "fallback:jaccard"
  },
  {
    "node_code_old": "01.019 DESC",
    "node_kind": "des_mat",
    "descripcion_corta": "DESBROCE TALUD EN ZONAS DE ACTUACION",
    "descripcion_larga": "",
    "unidad": "m2",
    "selected_product_code": "SB3105",
    "confidence": 0.0,
    "reason": "fallback:jaccard"
  },
  {
    "node_code_old": "01.020 DESC",
    "node_kind": "des_mat",
    "descripcion_corta": "DESMONTAJE Y REUBICACION  DE PAPELERAS",
    "descripcion_larga": "",
    "unidad": "UD",
    "selected_product_code": "MA5301",
    "confidence": 0.0,
    "reason": "fallback:jaccard"
  },
  {
    "node_code_old": "01.021 DESC",
    "node_kind": "des_mat",
    "descripcion_corta": "DESMONTAJE Y RETRAZADO DE INSTALACIONES DE GAS",
    "descripcion_larga": "",
    "unidad": "UD",
    "selected_product_code": "SB1401",
    "confidence": 0.0,
    "reason": "fallback:jaccard"
  },
  {
    "node_code_old": "01.022 DESC",
    "node_kind": "des_mat",
    "descripcion_corta": "DESMONTAJE CANCELA DE MALLA ELECTROSOLDADA",
    "descripcion_larga": "",
    "unidad": "UD",
    "selected_product_code": "MA3002",
    "confidence": 0.0,
    "reason": "fallback:jaccard"
  },
  {
    "node_code_old": "01.023 DESC",
    "node_kind": "des_mat",
    "descripcion_corta": "DESESCOMBRO MATERIAL ACOPIADO EN PATIO HACIA JULIAN ROMEA",
    "descripcion_larga": "",
    "unidad": "UD",
    "selected_product_code": "SB2303",
    "confidence": 0.0,
    "reason": "fallback:jaccard"
  },
  {
    "node_code_old": "01.024 DESC",
    "node_kind": "des_mat",
    "descripcion_corta": "EJEC CATAS DE INVESTIGACION EN FACHADA EXISTENTE C/ REPOS",
    "descripcion_larga": "",
    "unidad": "UD",
    "selected_product_code": "SB3105",
    "confidence": 0.0,
    "reason": "fallback:jaccard"
  },
  {
    "node_code_old": "01.025 DESC",
    "node_kind": "des_mat",
    "descripcion_corta": "EJEC CATA DE INVESTIGACION EN DESEMBARCO ESC EXTERIOR",
    "descripcion_larga": "",
    "unidad": "UD",
    "selected_product_code": "SB3105",
    "confidence": 0.0,
    "reason": "fallback:jaccard"
  },
  {
    "node_code_old": "01.018C DESC",
    "node_kind": "des_mat",
    "descripcion_corta": "DEMOLICION SOLERA EXTERIOR H. ARMADO",
    "descripcion_larga": "",
    "unidad": "M2",
    "selected_product_code": "MA5002",
    "confidence": 0.0,
    "reason": "fallback:jaccard"
  },
  {
    "node_code_old": "01.018B DESC",
    "node_kind": "des_mat",
    "descripcion_corta": "DEMOLICION PAVIMENTO EXTERIOR S/CAPA MORTERO",
    "descripcion_larga": "",
    "unidad": "M2",
    "selected_product_code": "MA5002",
    "confidence": 0.0,
    "reason": "fallback:jaccard"
  },
  {
    "node_code_old": "O LEVANTADO PELDANOS",
    "node_kind": "des_mat",
    "descripcion_corta": "LEVANTADO PELDANOS",
    "descripcion_larga": "",
    "unidad": "ml",
    "selected_product_code": "MA0101",
    "confidence": 0.0,
    "reason": "fallback:jaccard"
  },
  {
    "node_code_old": "O DEMOL MUROS",
    "node_kind": "des_mat",
    "descripcion_corta": "DEMOL MUROS PERIMETRALES",
    "descripcion_larga": "",
    "unidad": "M3",
    "selected_product_code": "MA4602",
    "confidence": 0.0,
    "reason": "fallback:jaccard"
  },
  {
    "node_code_old": "PP VARIOS",
    "node_kind": "des_mat",
    "descripcion_corta": "VARIOS, INDEFINICION",
    "descripcion_larga": "",
    "unidad": "PP",
    "selected_product_code": "CIIN1201",
    "confidence": 0.0,
    "reason": "fallback:jaccard"
  },
  {
    "node_code_old": "01.027 DESC",
    "node_kind": "des_mat",
    "descripcion_corta": "CORTE CABEZA MURO",
    "descripcion_larga": "",
    "unidad": "m3",
    "selected_product_code": "SM1104",
    "confidence": 0.0,
    "reason": "fallback:jaccard"
  },
  {
    "node_code_old": "O IMPERMEABILIZACION",
    "node_kind": "des_mat",
    "descripcion_corta": "IMPERMEABILIZACION",
    "descripcion_larga": "",
    "unidad": "m2",
    "selected_product_code": "MA3201",
    "confidence": 0.0,
    "reason": "fallback:jaccard"
  },
  {
    "node_code_old": "O PP VARIOS Y REMATE",
    "node_kind": "des_mat",
    "descripcion_corta": "INC. X REMATES, INDEFINICION",
    "descripcion_larga": "",
    "unidad": "PP",
    "selected_product_code": "MA0101",
    "confidence": 0.0,
    "reason": "fallback:jaccard"
  },
  {
    "node_code_old": "01.028 DESC",
    "node_kind": "des_mat",
    "descripcion_corta": "LEVANTADO PAV",
    "descripcion_larga": "",
    "unidad": "UD",
    "selected_product_code": "MA0101",
    "confidence": 0.0,
    "reason": "fallback:jaccard"
  },
  {
    "node_code_old": "02.001 DESC",
    "node_kind": "des_mat",
    "descripcion_corta": "NIVELACION Y RASANTEO PLATAFORMA. EXC. esp 10cm",
    "descripcion_larga": "",
    "unidad": "M2",
    "selected_product_code": "MA1701",
    "confidence": 0.0,
    "reason": "fallback:jaccard"
  },
  {
    "node_code_old": "02.002.1",
    "node_kind": "des_mat",
    "descripcion_corta": "EXTEND. Y COMPACT. MED MECAN. ZAHORRA ZA 0/20. esp 20cm",
    "descripcion_larga": "M2. Suministro y colocacion de subbase granular con zahorra artificial, compactacion al 98% del Proctor Modificado con medios mecanicos, con un espesor medio de 20 cm, hasta alcanzar una densidad seca no inferior al 98% del Proctor Modificado de la maxima obtenida en el ensayo Proctor Modificado.",
    "unidad": "M2",
    "selected_product_code": "SM3504",
    "confidence": 0.0,
    "reason": "fallback:jaccard"
  },
  {
    "node_code_old": "02.003 DESC",
    "node_kind": "des_mat",
    "descripcion_corta": "EXCAV POZOS/ ZANJAS C/ MED MECANICOS Y TRANSP A GESTOR AUTORIZAD",
    "descripcion_larga": "",
    "unidad": "M3",
    "selected_product_code": "MA4801",
    "confidence": 0.0,
    "reason": "fallback:jaccard"
  },
  {
    "node_code_old": "02.004 DESC",
    "node_kind": "des_mat",
    "descripcion_corta": "RELLENO EN TRASDOS C/ GRAVA MACHAQUEO O CANTO RODADO 20/30",
    "descripcion_larga": "",
    "unidad": "M3",
    "selected_product_code": "SB0302",
    "confidence": 0.0,
    "reason": "fallback:jaccard"
  },
  {
    "node_code_old": "03.001.1",
    "node_kind": "des_mat",
    "descripcion_corta": "HORMIGON LIMPIEZA Y NIVELACION HL-15/B/20 VERT. BOMBA",
    "descripcion_larga": "M3. Hormigon en masa para limpieza y nivelacion de fondos de cimentacion HL-15/B/20 de resistencia caracteristica a compresion 15 MPa (N/mm2), de consistencia blanda, tamano maximo del arido 20 mm, Totalmente realizado; i/p.p. de vertido por medio de grua torre o camion-bomba, vibrado y colocado. Segun normas EC-2, CE y CTE-SE-C. Componentes del hormigon con marcado CE y DdP (Declaracion de prestaciones) segun Reglamento (UE) 305/2011.",
    "unidad": "M3",
    "selected_product_code": "SM0607",
    "confidence": 0.0,
    "reason": "fallback:jaccard"
  },
  {
    "node_code_old": "03.002.1",
    "node_kind": "des_mat",
    "descripcion_corta": "H. ARM ENCOF ZAPATAS/ VIGAS HA30/F/20/XC4 VERT. BOMBA/ GRUA",
    "descripcion_larga": "M3. Hormigon armado, en relleno de zapatas, vigas riostras y zanjas de cimentacion, HA30/F/20/XC4, elaborado en central",
    "unidad": "M3",
    "selected_product_code": "SB1007",
    "confidence": 0.0,
    "reason": "fallback:jaccard"
  },
  {
    "node_code_old": "INCRVERMANUAL",
    "node_kind": "des_mat",
    "descripcion_corta": "INCRVERMANUAL",
    "descripcion_larga": "",
    "unidad": "UD",
    "selected_product_code": "MA0101",
    "confidence": 0.0,
    "reason": "fallback:jaccard"
  },
  {
    "node_code_old": "MOLOSA",
    "node_kind": "des_mat",
    "descripcion_corta": "MO LOSA",
    "descripcion_larga": "",
    "unidad": "M2",
    "selected_product_code": "MA0101",
    "confidence": 0.0,
    "reason": "fallback:jaccard"
  },
  {
    "node_code_old": "O INC. ALTURA",
    "node_kind": "des_mat",
    "descripcion_corta": "INC. ALTURA",
    "descripcion_larga": "",
    "unidad": "M2",
    "selected_product_code": "SB0302",
    "confidence": 0.0,
    "reason": "fallback:jaccard"
  },
  {
    "node_code_old": "PP REPERCUSION DIFIC",
    "node_kind": "des_mat",
    "descripcion_corta": "REPERCUSION X POCA MEDICION",
    "descripcion_larga": "",
    "unidad": "M2",
    "selected_product_code": "MA0101",
    "confidence": 0.0,
    "reason": "fallback:jaccard"
  },
  {
    "node_code_old": "P700800",
    "node_kind": "des_mat",
    "descripcion_corta": "JUNTA GUM I-3 DE 230 MM.",
    "descripcion_larga": "",
    "unidad": "ML",
    "selected_product_code": "CIMP1101",
    "confidence": 0.0,
    "reason": "fallback:jaccard"
  },
  {
    "node_code_old": "P325215",
    "node_kind": "des_mat",
    "descripcion_corta": "SEPARADORES HORMIGON 20 MM. C/A",
    "descripcion_larga": "",
    "unidad": "UD",
    "selected_product_code": "MA4602",
    "confidence": 0.0,
    "reason": "fallback:jaccard"
  },
  {
    "node_code_old": "O03.005",
    "node_kind": "des_mat",
    "descripcion_corta": "VERTIDO HORMIGON EN MUROS",
    "descripcion_larga": "",
    "unidad": "M3",
    "selected_product_code": "MA4602",
    "confidence": 0.0,
    "reason": "fallback:jaccard"
  },
  {
    "node_code_old": "O03.0051-ESPESOR",
    "node_kind": "des_mat",
    "descripcion_corta": "ENCOFRADO MURO A 2 CARAS I/ENCAMILLADO",
    "descripcion_larga": "",
    "unidad": "M2",
    "selected_product_code": "CIOI0501",
    "confidence": 0.0,
    "reason": "fallback:jaccard"
  },
  {
    "node_code_old": "O03.0054",
    "node_kind": "des_mat",
    "descripcion_corta": "INCR. ENCOFRADO TABLERO FENOLICO 1 PUESTA",
    "descripcion_larga": "",
    "unidad": "M2",
    "selected_product_code": "XC0401",
    "confidence": 0.0,
    "reason": "fallback:jaccard"
  },
  {
    "node_code_old": "03.007.1",
    "node_kind": "des_mat",
    "descripcion_corta": "ACERO LAMINADO S 275 JR PERF. PERFILES LAM/ CONF. GALV CALIENTE",
    "descripcion_larga": "KG. Acero laminado en caliente S-275-JR en estructura metalica en perfiles laminados o conformados con uniones soldadas, y/ o atornilladas, segun detalles de planos de estructura, incluyendo la unidad el corte, la elaboracion y el montaje, con la parte proporcional de soldaduras, cartelas, rigidizadores, placas de anclaje y apoyo, despuntes, piezas especiales, tensores, calzos, rotulas, etc. ",
    "unidad": "KG",
    "selected_product_code": "SB1001",
    "confidence": 0.0,
    "reason": "fallback:jaccard"
  },
  {
    "node_code_old": "HA30-",
    "node_kind": "des_mat",
    "descripcion_corta": "HA-30/B/20/XC2",
    "descripcion_larga": "",
    "unidad": "M3",
    "selected_product_code": "MA0101",
    "confidence": 0.0,
    "reason": "fallback:jaccard"
  },
  {
    "node_code_old": "O INC. XC4",
    "node_kind": "des_mat",
    "descripcion_corta": "INC. XC4",
    "descripcion_larga": "",
    "unidad": "M3",
    "selected_product_code": "MA0101",
    "confidence": 0.0,
    "reason": "fallback:jaccard"
  },
  {
    "node_code_old": "P324589",
    "node_kind": "des_mat",
    "descripcion_corta": "MALLA ELECT. 15X15  D.10",
    "descripcion_larga": "",
    "unidad": "M2",
    "selected_product_code": "MA3002",
    "confidence": 0.0,
    "reason": "fallback:jaccard"
  },
  {
    "node_code_old": "O PP VARIOS",
    "node_kind": "des_mat",
    "descripcion_corta": "INC. X INCLINADA, ENCOFRADO Y POCA MEDICION",
    "descripcion_larga": "",
    "unidad": "M2",
    "selected_product_code": "XC0401",
    "confidence": 0.0,
    "reason": "fallback:jaccard"
  },
  {
    "node_code_old": "04.000 DESC",
    "node_kind": "des_mat",
    "descripcion_corta": "TOMA DE MEDIDAS FACHADA EXISTE Y REPLANTEO PLOMOS NUEVA FACHADA",
    "descripcion_larga": "",
    "unidad": "UD",
    "selected_product_code": "MA5301",
    "confidence": 0.0,
    "reason": "fallback:jaccard"
  },
  {
    "node_code_old": "04.001 DESC",
    "node_kind": "des_mat",
    "descripcion_corta": "AISL.POLIEST.EXTR. DANOPREN PR-80, CAMARA",
    "descripcion_larga": "",
    "unidad": "M2",
    "selected_product_code": "MA0101",
    "confidence": 0.0,
    "reason": "fallback:jaccard"
  },
  {
    "node_code_old": "O MO SETAS",
    "node_kind": "des_mat",
    "descripcion_corta": "MO SETAS",
    "descripcion_larga": "",
    "unidad": "M2",
    "selected_product_code": "MA0101",
    "confidence": 0.0,
    "reason": "fallback:jaccard"
  },
  {
    "node_code_old": "04.002 DESC",
    "node_kind": "des_mat",
    "descripcion_corta": "MURO DE SILLERIA GRANITO GRIS QUINTANA SELEC ABUJARDADO 210x36x7",
    "descripcion_larga": "",
    "unidad": "M2",
    "selected_product_code": "SB2104",
    "confidence": 0.0,
    "reason": "fallback:jaccard"
  },
  {
    "node_code_old": "O TABLERO -DS2DS2.1",
    "node_kind": "des_mat",
    "descripcion_corta": "TABLERO",
    "descripcion_larga": "",
    "unidad": "M2",
    "selected_product_code": "MA0101",
    "confidence": 0.0,
    "reason": "fallback:jaccard"
  },
  {
    "node_code_old": "O LAMINA NODULOS-2A2",
    "node_kind": "partida",
    "descripcion_corta": "LAMINA NODULOS",
    "descripcion_larga": "",
    "unidad": "M2",
    "selected_product_code": "MA0101",
    "confidence": 0.0,
    "reason": "fallback:jaccard"
  },
  {
    "node_code_old": "O FACHADA ZINC-2A2A.",
    "node_kind": "des_mat",
    "descripcion_corta": "FACHADA ZINC",
    "descripcion_larga": "",
    "unidad": "M2",
    "selected_product_code": "MA4201",
    "confidence": 0.0,
    "reason": "fallback:jaccard"
  },
  {
    "node_code_old": "O KG ACERO",
    "node_kind": "des_mat",
    "descripcion_corta": "ACERO",
    "descripcion_larga": "",
    "unidad": "KG",
    "selected_product_code": "MA0102",
    "confidence": 0.0,
    "reason": "fallback:jaccard"
  },
  {
    "node_code_old": "O ANCLAJES Y CARTELA",
    "node_kind": "des_mat",
    "descripcion_corta": "ANCLAJES Y CARTELAS",
    "descripcion_larga": "",
    "unidad": "ML",
    "selected_product_code": "MA1901",
    "confidence": 0.0,
    "reason": "fallback:jaccard"
  },
  {
    "node_code_old": "O LSKDFHHDFSO",
    "node_kind": "des_mat",
    "descripcion_corta": "OPCION. MURO SILLERIA GRANITO GRIS QUINT SEL ABUJARDADO 210x36x5",
    "descripcion_larga": "",
    "unidad": "m2",
    "selected_product_code": "SM1104",
    "confidence": 0.0,
    "reason": "fallback:jaccard"
  },
  {
    "node_code_old": "05.001 DESC",
    "node_kind": "des_mat",
    "descripcion_corta": "PAVIMENTO ADOQUIN GRANITO GRIS QUINTANA 10x10x10 s/MTO CTO/ AREN",
    "descripcion_larga": "",
    "unidad": "M2",
    "selected_product_code": "MA4308",
    "confidence": 0.0,
    "reason": "fallback:jaccard"
  },
  {
    "node_code_old": "05.002 DESC",
    "node_kind": "des_mat",
    "descripcion_corta": "PAV. BALDOSAS GRANITO GRIS QUINTANA ABUJARD 7cm s/MTO CTO/ AREN",
    "descripcion_larga": "",
    "unidad": "M2",
    "selected_product_code": "MA1602",
    "confidence": 0.0,
    "reason": "fallback:jaccard"
  },
  {
    "node_code_old": "05.003 DESC",
    "node_kind": "des_mat",
    "descripcion_corta": "BORDILLO GRANITO GRIS QUINTANA ABUJARDADO 12x20 cm",
    "descripcion_larga": "",
    "unidad": "M",
    "selected_product_code": "MA1501",
    "confidence": 0.0,
    "reason": "fallback:jaccard"
  },
  {
    "node_code_old": "05.004 DESC",
    "node_kind": "des_mat",
    "descripcion_corta": "BORDILLO CURVO GRANITO GRIS QUINTANA  ABUJARDADO 12x20 cm",
    "descripcion_larga": "",
    "unidad": "M",
    "selected_product_code": "MA1501",
    "confidence": 0.0,
    "reason": "fallback:jaccard"
  },
  {
    "node_code_old": "O BANCO GRANITO",
    "node_kind": "des_mat",
    "descripcion_corta": "BANCO GRANITO",
    "descripcion_larga": "",
    "unidad": "ml",
    "selected_product_code": "MA0101",
    "confidence": 0.0,
    "reason": "fallback:jaccard"
  },
  {
    "node_code_old": "05.006 DESC",
    "node_kind": "des_mat",
    "descripcion_corta": "PELDANO ENTERIZO GRANITO GRIS QUINTANA 45x22,5",
    "descripcion_larga": "",
    "unidad": "M",
    "selected_product_code": "MA1501",
    "confidence": 0.0,
    "reason": "fallback:jaccard"
  },
  {
    "node_code_old": "O KG PERFILES PLETIN",
    "node_kind": "des_mat",
    "descripcion_corta": "PLETINA 200.10",
    "descripcion_larga": "",
    "unidad": "ml",
    "selected_product_code": "MA0101",
    "confidence": 0.0,
    "reason": "fallback:jaccard"
  },
  {
    "node_code_old": "O GARROTAS VARIOS",
    "node_kind": "des_mat",
    "descripcion_corta": "GARROTAS VARIOS",
    "descripcion_larga": "",
    "unidad": "PP",
    "selected_product_code": "CIIN1201",
    "confidence": 0.0,
    "reason": "fallback:jaccard"
  },
  {
    "node_code_old": "CCOLA",
    "node_kind": "des_mat",
    "descripcion_corta": "CEMENTO COLA",
    "descripcion_larga": "",
    "unidad": "M2",
    "selected_product_code": "MA1503",
    "confidence": 0.0,
    "reason": "fallback:jaccard"
  },
  {
    "node_code_old": "05.008 DESC",
    "node_kind": "des_mat",
    "descripcion_corta": "PELDANO 28x17,5 GRANITO GRIS QUINTANA esp 5cm c/MTO HID CTO/AR",
    "descripcion_larga": "",
    "unidad": "M",
    "selected_product_code": "MA1501",
    "confidence": 0.0,
    "reason": "fallback:jaccard"
  },
  {
    "node_code_old": "05.009 DESC",
    "node_kind": "des_mat",
    "descripcion_corta": "PAV GRANITO GRIS QUINTANA esp 5cm c/MTO HIDROF CTO Y ARENA",
    "descripcion_larga": "",
    "unidad": "M2",
    "selected_product_code": "MA1501",
    "confidence": 0.0,
    "reason": "fallback:jaccard"
  },
  {
    "node_code_old": "% DESC. INGEPIEDRA",
    "node_kind": "des_mat",
    "descripcion_corta": "DESC. INGEPIEDRA",
    "descripcion_larga": "",
    "unidad": "UD",
    "selected_product_code": "MA0101",
    "confidence": 0.0,
    "reason": "fallback:jaccard"
  },
  {
    "node_code_old": "ARENA",
    "node_kind": "des_mat",
    "descripcion_corta": "ARENA",
    "descripcion_larga": "",
    "unidad": "M3",
    "selected_product_code": "MA0101",
    "confidence": 0.0,
    "reason": "fallback:jaccard"
  },
  {
    "node_code_old": "RECRMOR",
    "node_kind": "des_mat",
    "descripcion_corta": "RECRECIDO MORTERO 6CM CON MATERIALES - RECR CACERES",
    "descripcion_larga": "",
    "unidad": "m2",
    "selected_product_code": "SM2905",
    "confidence": 0.0,
    "reason": "fallback:jaccard"
  },
  {
    "node_code_old": "05.010 DESC",
    "node_kind": "des_mat",
    "descripcion_corta": "PAV ADOQUIN GRANITO GRIS QUINTANA 5x5x5 s/CAMA ARENA Y REJUNTADO",
    "descripcion_larga": "",
    "unidad": "M2",
    "selected_product_code": "MA1501",
    "confidence": 0.0,
    "reason": "fallback:jaccard"
  },
  {
    "node_code_old": "02.002 DESC",
    "node_kind": "des_mat",
    "descripcion_corta": "EXTEND. Y COMPACT. MED MECAN. ZAHORRA ZA 0/20. esp 20cm",
    "descripcion_larga": "",
    "unidad": "M2",
    "selected_product_code": "MA1701",
    "confidence": 0.0,
    "reason": "fallback:jaccard"
  },
  {
    "node_code_old": "O SOLERA-2",
    "node_kind": "des_mat",
    "descripcion_corta": "SOLERA 10 CM",
    "descripcion_larga": "",
    "unidad": "M2",
    "selected_product_code": "MA0101",
    "confidence": 0.0,
    "reason": "fallback:jaccard"
  },
  {
    "node_code_old": "BOMBEO",
    "node_kind": "des_mat",
    "descripcion_corta": "BOMBEO",
    "descripcion_larga": "",
    "unidad": "M3",
    "selected_product_code": "SB1006",
    "confidence": 0.0,
    "reason": "fallback:jaccard"
  },
  {
    "node_code_old": "CONECTORES",
    "node_kind": "des_mat",
    "descripcion_corta": "CONECTORES",
    "descripcion_larga": "",
    "unidad": "PP",
    "selected_product_code": "MA0101",
    "confidence": 0.0,
    "reason": "fallback:jaccard"
  },
  {
    "node_code_old": "MO SOLERA",
    "node_kind": "des_mat",
    "descripcion_corta": "MO SOLERA",
    "descripcion_larga": "",
    "unidad": "M2",
    "selected_product_code": "MA0101",
    "confidence": 0.0,
    "reason": "fallback:jaccard"
  },
  {
    "node_code_old": "POLIETILENO-A",
    "node_kind": "des_mat",
    "descripcion_corta": "POLIETILENO G-400 PLASTICO",
    "descripcion_larga": "",
    "unidad": "M2",
    "selected_product_code": "MA0101",
    "confidence": 0.0,
    "reason": "fallback:jaccard"
  },
  {
    "node_code_old": "HA25",
    "node_kind": "des_mat",
    "descripcion_corta": "HA-25/B/20/XC2",
    "descripcion_larga": "",
    "unidad": "M3",
    "selected_product_code": "MA0101",
    "confidence": 0.0,
    "reason": "fallback:jaccard"
  },
  {
    "node_code_old": "P324435",
    "node_kind": "des_mat",
    "descripcion_corta": "MALLA ELECT. 15X15  D.6",
    "descripcion_larga": "",
    "unidad": "M2",
    "selected_product_code": "MA3002",
    "confidence": 0.0,
    "reason": "fallback:jaccard"
  },
  {
    "node_code_old": "O ARIPAQ",
    "node_kind": "des_mat",
    "descripcion_corta": "ARIPAQ 10 cm.",
    "descripcion_larga": "",
    "unidad": "M2",
    "selected_product_code": "MA0101",
    "confidence": 0.0,
    "reason": "fallback:jaccard"
  },
  {
    "node_code_old": "O PRECIO M2 VIDRIO I",
    "node_kind": "des_mat",
    "descripcion_corta": "VIDRIO+INOX.",
    "descripcion_larga": "",
    "unidad": "M2",
    "selected_product_code": "MA1401",
    "confidence": 0.0,
    "reason": "fallback:jaccard"
  },
  {
    "node_code_old": "O PUERTAS INOX",
    "node_kind": "des_mat",
    "descripcion_corta": "PUERTA DOBLE INOX",
    "descripcion_larga": "",
    "unidad": "UD",
    "selected_product_code": "MA1401",
    "confidence": 0.0,
    "reason": "fallback:jaccard"
  },
  {
    "node_code_old": "O PP ELECTRICA",
    "node_kind": "des_mat",
    "descripcion_corta": "PP ELECTRICA",
    "descripcion_larga": "",
    "unidad": "UD",
    "selected_product_code": "QA0101",
    "confidence": 0.0,
    "reason": "fallback:jaccard"
  },
  {
    "node_code_old": "06.002 DESC",
    "node_kind": "des_mat",
    "descripcion_corta": "FELPUDO ENTRADA EMCO. 522 GK 22 mm c/ MARCO PERIMETRAL",
    "descripcion_larga": "",
    "unidad": "M2",
    "selected_product_code": "MA4307",
    "confidence": 0.0,
    "reason": "fallback:jaccard"
  },
  {
    "node_code_old": "07.001.1",
    "node_kind": "des_mat",
    "descripcion_corta": "BAJANTE PVC PLUVIALES 90 mm",
    "descripcion_larga": "M. Bajante de PVC de pluviales, UNE-EN-1453:1996, de 90 mm de diametro, con sistema de union por junta elastica, colocada con abrazaderas metalicas, instalada, incluso con p.p. de piezas especiales de PVC, funcionando.  Segun CTE-HS-5.",
    "unidad": "M",
    "selected_product_code": "SM2104",
    "confidence": 0.0,
    "reason": "fallback:jaccard"
  },
  {
    "node_code_old": "07.002 DESC",
    "node_kind": "des_mat",
    "descripcion_corta": "BAJANTE ZINC 100 mm",
    "descripcion_larga": "",
    "unidad": "M",
    "selected_product_code": "MA0705",
    "confidence": 0.0,
    "reason": "fallback:jaccard"
  },
  {
    "node_code_old": "P760012",
    "node_kind": "des_mat",
    "descripcion_corta": "HM-20/B/20/I",
    "descripcion_larga": "",
    "unidad": "M3",
    "selected_product_code": "CIOI0501",
    "confidence": 0.0,
    "reason": "fallback:jaccard"
  },
  {
    "node_code_old": "P371040",
    "node_kind": "des_mat",
    "descripcion_corta": "GRAVILLA DE 6/20 MM.",
    "descripcion_larga": "",
    "unidad": "M3",
    "selected_product_code": "CIMP1101",
    "confidence": 0.0,
    "reason": "fallback:jaccard"
  },
  {
    "node_code_old": "O02.039",
    "node_kind": "des_mat",
    "descripcion_corta": "TUBERIA DE DRENAJE DE PVC D.150",
    "descripcion_larga": "",
    "unidad": "ML",
    "selected_product_code": "MA5105",
    "confidence": 0.0,
    "reason": "fallback:jaccard"
  },
  {
    "node_code_old": "P661410",
    "node_kind": "des_mat",
    "descripcion_corta": "TUBERIA PVC DRENAJE D.150",
    "descripcion_larga": "",
    "unidad": "ML",
    "selected_product_code": "MA5105",
    "confidence": 0.0,
    "reason": "fallback:jaccard"
  },
  {
    "node_code_old": "O05.004302",
    "node_kind": "des_mat",
    "descripcion_corta": "GEOTEXTIL",
    "descripcion_larga": "",
    "unidad": "M2",
    "selected_product_code": "MA3001",
    "confidence": 0.0,
    "reason": "fallback:jaccard"
  },
  {
    "node_code_old": "07.004 DESC",
    "node_kind": "des_mat",
    "descripcion_corta": "CANALETA HORM POLIMERO c/REJ FUNDICION B125 ACO SELF 100 H145",
    "descripcion_larga": "",
    "unidad": "M",
    "selected_product_code": "MA0202",
    "confidence": 0.0,
    "reason": "fallback:jaccard"
  },
  {
    "node_code_old": "O EXCAV SOLERA VARIO",
    "node_kind": "des_mat",
    "descripcion_corta": "MO COLOCACION EXCAV SOLERA VARIOS Y POCA MEDICION",
    "descripcion_larga": "",
    "unidad": "ML",
    "selected_product_code": "SB0404",
    "confidence": 0.0,
    "reason": "fallback:jaccard"
  },
  {
    "node_code_old": "P661312.01",
    "node_kind": "des_mat",
    "descripcion_corta": "TUBERIA PVC RIGIDO S.D. 125 MM. TEJA",
    "descripcion_larga": "",
    "unidad": "ML",
    "selected_product_code": "MA5105",
    "confidence": 0.0,
    "reason": "fallback:jaccard"
  },
  {
    "node_code_old": "O02.03101",
    "node_kind": "des_mat",
    "descripcion_corta": "TUBERIA PVC D.125 MM. ENTERRADA",
    "descripcion_larga": "",
    "unidad": "ML",
    "selected_product_code": "MA5105",
    "confidence": 0.0,
    "reason": "fallback:jaccard"
  },
  {
    "node_code_old": "P371030",
    "node_kind": "des_mat",
    "descripcion_corta": "ARENA DE RIO DE 0/6 MM.",
    "descripcion_larga": "",
    "unidad": "M3",
    "selected_product_code": "CIMP1101",
    "confidence": 0.0,
    "reason": "fallback:jaccard"
  },
  {
    "node_code_old": "P120000",
    "node_kind": "des_mat",
    "descripcion_corta": "TRANSPORTE DE TIERRAS",
    "descripcion_larga": "",
    "unidad": "M3",
    "selected_product_code": "SM2701",
    "confidence": 0.0,
    "reason": "fallback:jaccard"
  },
  {
    "node_code_old": "FLUT 180 G2",
    "node_kind": "des_mat",
    "descripcion_corta": "COMPRA NETO SIN MARGEN INSTALADOR X TFNO SALTOKI",
    "descripcion_larga": "",
    "unidad": "UD",
    "selected_product_code": "XC0501",
    "confidence": 0.0,
    "reason": "fallback:jaccard"
  },
  {
    "node_code_old": "LITFLOOD1",
    "node_kind": "des_mat",
    "descripcion_corta": "COMPRA NETO SIN MARGEN INSTALADOR X TFNO SALTOKI",
    "descripcion_larga": "",
    "unidad": "UD",
    "selected_product_code": "XC0501",
    "confidence": 0.0,
    "reason": "fallback:jaccard"
  },
  {
    "node_code_old": "MO BANADOR",
    "node_kind": "des_mat",
    "descripcion_corta": "MO BANADOR",
    "descripcion_larga": "",
    "unidad": "UD",
    "selected_product_code": "MA0101",
    "confidence": 0.0,
    "reason": "fallback:jaccard"
  },
  {
    "node_code_old": "SHOT 80 G2",
    "node_kind": "des_mat",
    "descripcion_corta": "SHOT 80 G2",
    "descripcion_larga": "",
    "unidad": "UD",
    "selected_product_code": "MA0101",
    "confidence": 0.0,
    "reason": "fallback:jaccard"
  },
  {
    "node_code_old": "%SUB25",
    "node_kind": "des_mat",
    "descripcion_corta": "%SUB25",
    "descripcion_larga": "",
    "unidad": "UD",
    "selected_product_code": "MA0101",
    "confidence": 0.0,
    "reason": "fallback:jaccard"
  },
  {
    "node_code_old": "FLUIDO",
    "node_kind": "des_mat",
    "descripcion_corta": "INC. FLUIDO",
    "descripcion_larga": "",
    "unidad": "M3",
    "selected_product_code": "MA0101",
    "confidence": 0.0,
    "reason": "fallback:jaccard"
  },
  {
    "node_code_old": "SEPARADORES-22",
    "node_kind": "des_mat",
    "descripcion_corta": "SEPARADORES HORMIGON 50 MM. C/A",
    "descripcion_larga": "",
    "unidad": "UD",
    "selected_product_code": "MA4602",
    "confidence": 0.0,
    "reason": "fallback:jaccard"
  },
  {
    "node_code_old": "ACERO CORRUGADO",
    "node_kind": "des_mat",
    "descripcion_corta": "ACERO AEH-500-S ( VARIOS CALIBRES )",
    "descripcion_larga": "",
    "unidad": "KG",
    "selected_product_code": "CIIN1201",
    "confidence": 0.0,
    "reason": "fallback:jaccard"
  },
  {
    "node_code_old": "VERTIDO H. CIMENTACI",
    "node_kind": "des_mat",
    "descripcion_corta": "VERTIDO HORMIGON EN CIMENTACION",
    "descripcion_larga": "",
    "unidad": "M3",
    "selected_product_code": "MA3103",
    "confidence": 0.0,
    "reason": "fallback:jaccard"
  },
  {
    "node_code_old": "O EXCAVACION",
    "node_kind": "des_mat",
    "descripcion_corta": "EXCAVACION",
    "descripcion_larga": "",
    "unidad": "M3",
    "selected_product_code": "MA0101",
    "confidence": 0.0,
    "reason": "fallback:jaccard"
  },
  {
    "node_code_old": "O HORM. LIMPIEZA",
    "node_kind": "des_mat",
    "descripcion_corta": "HORMIGON LIMPIEZA",
    "descripcion_larga": "",
    "unidad": "M3",
    "selected_product_code": "MA4602",
    "confidence": 0.0,
    "reason": "fallback:jaccard"
  },
  {
    "node_code_old": "HM-20",
    "node_kind": "des_mat",
    "descripcion_corta": "HM-20",
    "descripcion_larga": "",
    "unidad": "M3",
    "selected_product_code": "MA0101",
    "confidence": 0.0,
    "reason": "fallback:jaccard"
  },
  {
    "node_code_old": "VERT HOR LIMP",
    "node_kind": "des_mat",
    "descripcion_corta": "VERTIDO HORMIGON DE LIMPIEZA",
    "descripcion_larga": "",
    "unidad": "M3",
    "selected_product_code": "MA4602",
    "confidence": 0.0,
    "reason": "fallback:jaccard"
  },
  {
    "node_code_old": "O ANCLAJES Y VARIOS",
    "node_kind": "des_mat",
    "descripcion_corta": "ANCLAJES Y VARIOS",
    "descripcion_larga": "",
    "unidad": "PP",
    "selected_product_code": "MA1901",
    "confidence": 0.0,
    "reason": "fallback:jaccard"
  },
  {
    "node_code_old": "PTO. LUZ EXT",
    "node_kind": "des_mat",
    "descripcion_corta": "PTO. LUZ EXT",
    "descripcion_larga": "",
    "unidad": "UD",
    "selected_product_code": "MA0101",
    "confidence": 0.0,
    "reason": "fallback:jaccard"
  },
  {
    "node_code_old": "09.001 DESC",
    "node_kind": "des_mat",
    "descripcion_corta": "TRASPLANTADO DE ARBOL",
    "descripcion_larga": "",
    "unidad": "UD",
    "selected_product_code": "CIMP1101",
    "confidence": 0.0,
    "reason": "fallback:jaccard"
  },
  {
    "node_code_old": "09.002 DESC",
    "node_kind": "des_mat",
    "descripcion_corta": "SUM Y PLANT ACACIA (ROBINIA PSEUDOACACIA) diam 14cm",
    "descripcion_larga": "",
    "unidad": "UD",
    "selected_product_code": "MA1701",
    "confidence": 0.0,
    "reason": "fallback:jaccard"
  },
  {
    "node_code_old": "CONTROL DE CALIDAD.1",
    "node_kind": "des_mat",
    "descripcion_corta": "CONTROL DE CALIDAD",
    "descripcion_larga": "",
    "unidad": "ud",
    "selected_product_code": "CITE0401",
    "confidence": 0.0,
    "reason": "fallback:jaccard"
  },
  {
    "node_code_old": "GESTION DE RESIDUOS.",
    "node_kind": "des_mat",
    "descripcion_corta": "GESTION DE RESIDUOS",
    "descripcion_larga": "",
    "unidad": "ud",
    "selected_product_code": "MA2506",
    "confidence": 0.0,
    "reason": "fallback:jaccard"
  },
  {
    "node_code_old": "P SFJDGSNNJDGS",
    "node_kind": "des_mat",
    "descripcion_corta": "PAVIMENTO ADOQUIN GRANITO CARA SUPERIOR FLAMEADA Y EL RESTO CIZALLADAS, EN FORMATO 10x10x6cm.",
    "descripcion_larga": "",
    "unidad": "M2",
    "selected_product_code": "MA3303",
    "confidence": 0.0,
    "reason": "fallback:jaccard"
  },
  {
    "node_code_old": "%SUB20",
    "node_kind": "des_mat",
    "descripcion_corta": "%SUB20",
    "descripcion_larga": "",
    "unidad": "UD",
    "selected_product_code": "MA0101",
    "confidence": 0.0,
    "reason": "fallback:jaccard"
  },
  {
    "node_code_old": "SEGURIDAD Y SALUD.1",
    "node_kind": "des_mat",
    "descripcion_corta": "SEGURIDAD Y SALUD",
    "descripcion_larga": "",
    "unidad": "ud",
    "selected_product_code": "MA3604",
    "confidence": 0.0,
    "reason": "fallback:jaccard"
  }
]